rs3clans/__init__.py
rs3clans/clans.py
rs3clans/players.py
rs3clans-1.1.3.dist-info/LICENSE
rs3clans-1.1.3.dist-info/WHEEL
rs3clans-1.1.3.dist-info/METADATA
rs3clans-1.1.3.dist-info/RECORD
